kopi/Back_brewcson.py
kopi/Bak2_main.py
kopi/Bak_brewcson.py
kopi/Bak_htmlcanvas.py
kopi/Bak_killme.py
kopi/Bak_main.py
kopi/Bak_misc.py
kopi/Bak_myascii85.py
kopi/Bak_mycolor.py
kopi/Bak_mycson.py
kopi/Bak_myfont.py
kopi/Bak_myimage.py
kopi/Bak_mypretty.py
kopi/Bak_pdf.py
kopi/Tool_CsonToDictScrip.py
kopi/Tool_Dict2HardClass.py
kopi/Tool_NotGood_ParseDictIteration2ClassScript.py
kopi/Tool_ParseDictIteration2ClassScript.py
kopi/Tool_readfile.py
kopi/Tool_replacetab.py
kopi/__init__.py
kopi/__main.py
kopi/__version__.py
kopi/brewcson.py
kopi/color.py
kopi/dict2obj.py
kopi/htmlcanvas.py
kopi/killme.py
kopi/killmeclass.py
kopi/main.py
kopi/misc.py
kopi/myascii85.py
kopi/mycson.py
kopi/myfont.py
kopi/mygeneratecolormap.py
kopi/myglobal.py
kopi/myimage.py
kopi/mypretty.py
kopi/obs_mycson.py
kopi/obsolete_brewcson.py
kopi/obsolete_previously_destroyed_brewcson.py
kopi/pdf.py
kopi/plotscript.py
kopi/postscript.py
kopi/thisclass.py
kopi/wii.py
kopi-0.18.5.dist-info/DESCRIPTION.rst
kopi-0.18.5.dist-info/METADATA
kopi-0.18.5.dist-info/RECORD
kopi-0.18.5.dist-info/WHEEL
kopi-0.18.5.dist-info/metadata.json
kopi-0.18.5.dist-info/top_level.txt
